mplhep_data/__init__.py
mplhep_data/version.py
mplhep_data/fonts/firamath/FiraMath-Bold.otf
mplhep_data/fonts/firamath/FiraMath-Book.otf
mplhep_data/fonts/firamath/FiraMath-ExtraBold.otf
mplhep_data/fonts/firamath/FiraMath-ExtraLight.otf
mplhep_data/fonts/firamath/FiraMath-Heavy.otf
mplhep_data/fonts/firamath/FiraMath-Light.otf
mplhep_data/fonts/firamath/FiraMath-Medium.otf
mplhep_data/fonts/firamath/FiraMath-Regular.otf
mplhep_data/fonts/firamath/FiraMath-SemiBold.otf
mplhep_data/fonts/firamath/FiraMath-Thin.otf
mplhep_data/fonts/firamath/FiraMath-Ultra.otf
mplhep_data/fonts/firamath/FiraMath-UltraLight.otf
mplhep_data/fonts/firamath/LICENSE_FiraMath
mplhep_data/fonts/firasans/FiraMono-Bold.ttf
mplhep_data/fonts/firasans/FiraMono-Medium.ttf
mplhep_data/fonts/firasans/FiraMono-Regular.ttf
mplhep_data/fonts/firasans/FiraSans-Black.ttf
mplhep_data/fonts/firasans/FiraSans-BlackItalic.ttf
mplhep_data/fonts/firasans/FiraSans-Bold.ttf
mplhep_data/fonts/firasans/FiraSans-BoldItalic.ttf
mplhep_data/fonts/firasans/FiraSans-ExtraBold.ttf
mplhep_data/fonts/firasans/FiraSans-ExtraBoldItalic.ttf
mplhep_data/fonts/firasans/FiraSans-ExtraLight.ttf
mplhep_data/fonts/firasans/FiraSans-ExtraLightItalic.ttf
mplhep_data/fonts/firasans/FiraSans-Italic.ttf
mplhep_data/fonts/firasans/FiraSans-Light.ttf
mplhep_data/fonts/firasans/FiraSans-LightItalic.ttf
mplhep_data/fonts/firasans/FiraSans-Medium.ttf
mplhep_data/fonts/firasans/FiraSans-MediumItalic.ttf
mplhep_data/fonts/firasans/FiraSans-Regular.ttf
mplhep_data/fonts/firasans/FiraSans-SemiBold.ttf
mplhep_data/fonts/firasans/FiraSans-SemiBoldItalic.ttf
mplhep_data/fonts/firasans/FiraSans-Thin.ttf
mplhep_data/fonts/firasans/FiraSans-ThinItalic.ttf
mplhep_data/fonts/firasans/LICENSE_FiraSans
mplhep_data/fonts/latinmodernmath/LICENSE_LMMath
mplhep_data/fonts/latinmodernmath/latinmodern-math.otf
mplhep_data/fonts/latinmodernroman/LICENSE_LMRoman
mplhep_data/fonts/latinmodernroman/lmroman10-bold.otf
mplhep_data-0.0.4.dist-info/LICENSE
mplhep_data-0.0.4.dist-info/METADATA
mplhep_data-0.0.4.dist-info/WHEEL
mplhep_data-0.0.4.dist-info/top_level.txt
mplhep_data-0.0.4.dist-info/RECORD
