Metadata-Version: 2.1
Name: mplhep_data
Version: 0.0.4
Summary: Font (Data) sub-package for mplhep
Home-page: https://github.com/Scikit-HEP/mplhep_data
Author: Andrzej Novak
Author-email: novak5andrzej@gmail.com
Maintainer: The Scikit-HEP admins
Maintainer-email: scikit-hep-admins@googlegroups.com
License: MIT
Platform: Any
Classifier: Development Status :: 1 - Planning
Classifier: Intended Audience :: Developers
Classifier: Intended Audience :: Science/Research
Classifier: License :: OSI Approved :: MIT License
Classifier: Operating System :: OS Independent
Classifier: Programming Language :: Python
Classifier: Programming Language :: Python :: 3
Classifier: Programming Language :: Python :: 3 :: Only
Classifier: Programming Language :: Python :: 3.8
Classifier: Programming Language :: Python :: 3.9
Classifier: Programming Language :: Python :: 3.10
Classifier: Programming Language :: Python :: 3.11
Classifier: Programming Language :: Python :: 3.12
Classifier: Topic :: Scientific/Engineering
Requires-Python: >=3.8
License-File: LICENSE
Provides-Extra: dev
Requires-Dist: pytest>=4.6; extra == "dev"
Provides-Extra: test
Requires-Dist: pytest>=4.6; extra == "test"
